Workbook

Sheet netflix_titles
A1: show_id | B1: type | C1: title | D1: director | E1: cast | F1: country | G1: date_added | H1: release_year | I1: rating | J1: duration | K1: listed_in | L1: description
A2: s1 | B2: Movie | C2: Dick Johnson Is Dead | D2: Kirsten Johnson | E2: unknown | F2: United States | G2: 44440 | H2: 2020 | I2: PG-13 | J2: 90 min | K2: Documentaries | L2: As her father nears the end of his life, filmmaker Kirsten Johnson stages his death in inventive and comical ways to help them both face the inevitable.
A3: s2 | B3: TV Show | C3: Blood & Water | D3: unknown | E3: Ama Qamata, Khosi Ngema, Gail Mabalane, Thabang Molaba, Dillon Windvogel, Natasha Thahane, Arno Greeff, Xolile Tshabalala, Getmore Sithole, Cindy Mahlangu, Ryle De Morny, Greteli Fincham, Sello Maake Ka-Ncube, Odwa Gwanya, Mekaila Mathys, Sandi Schultz, Duane Williams, Shamilla Miller, Patrick Mofokeng | F3: South Africa | G3: 44441 | H3: 2021 | I3: TV-MA | J3: 2 Seasons | K3: International TV Shows, TV Dramas, TV Mysteries | L3: After crossing paths at a party, a Cape Town teen sets out to prove whether a private-school swimming star is her sister who was abducted at birth.
A4: s3 | B4: TV Show | C4: Ganglands | D4: Julien Leclercq | E4: Sami Bouajila, Tracy Gotoas, Samuel Jouy, Nabiha Akkari, Sofia Lesaffre, Salim Kechiouche, Noureddine Farihi, Geert Van Rampelberg, Bakary Diombera | F4: unknown | G4: 44442 | H4: 2021 | I4: TV-MA | J4: 1 Season | K4: Crime TV Shows, International TV Shows, TV Action & Adventure | L4: To protect his family from a powerful drug lord, skilled thief Mehdi and his expert team of robbers are pulled into a violent and deadly turf war.
A5: s4 | B5: TV Show | C5: Jailbirds New Orleans | D5: unknown | E5: unknown | F5: unknown | G5: 44443 | H5: 2021 | I5: TV-MA | J5: 1 Season | K5: Docuseries, Reality TV | L5: Feuds, flirtations and toilet talk go down among the incarcerated women at the Orleans Justice Center in New Orleans on this gritty reality series.
A6: s5 | B6: TV Show | C6: Kota Factory | D6: unknown | E6: Mayur More, Jitendra Kumar, Ranjan Raj, Alam Khan, Ahsaas Channa, Revathi Pillai, Urvi Singh, Arun Kumar | F6: India | G6: 44444 | H6: 2021 | I6: TV-MA | J6: 2 Seasons | K6: International TV Shows, Romantic TV Shows, TV Comedies | L6: In a city of coaching centers known to train Indiaâ€™s finest collegiate minds, an earnest but unexceptional student and his friends navigate campus life.
A7: s6 | B7: TV Show | C7: Midnight Mass | D7: Mike Flanagan | E7: Kate Siegel, Zach Gilford, Hamish Linklater, Henry Thomas, Kristin Lehman, Samantha Sloyan, Igby Rigney, Rahul Kohli, Annarah Cymone, Annabeth Gish, Alex Essoe, Rahul Abburi, Matt Biedel, Michael Trucco, Crystal Balint, Louis Oliver | F7: unknown | G7: 44445 | H7: 2021 | I7: TV-MA | J7: 1 Season | K7: TV Dramas, TV Horror, TV Mysteries | L7: The arrival of a charismatic young priest brings glorious miracles, ominous mysteries and renewed religious fervor to a dying town desperate to believe.
A8: s7 | B8: Movie | C8: My Little Pony: A New Generation | D8: Robert Cullen, JosÃ© Luis Ucha | E8: Vanessa Hudgens, Kimiko Glenn, James Marsden, Sofia Carson, Liza Koshy, Ken Jeong, Elizabeth Perkins, Jane Krakowski, Michael McKean, Phil LaMarr | F8: unknown | G8: 44446 | H8: 2021 | I8: PG | J8: 91 min | K8: Children & Family Movies | L8: Equestria's divided. But a bright-eyed hero believes Earth Ponies, Pegasi and Unicorns should be pals â€” and, hoof to heart, sheâ€™s determined to prove it.
A9: s8 | B9: Movie | C9: Sankofa | D9: Haile Gerima | E9: Kofi Ghanaba, Oyafunmike Ogunlano, Alexandra Duah, Nick Medley, Mutabaruka, Afemo Omilami, Reggie Carter, Mzuri | F9: United States, Ghana, Burkina Faso, United Kingdom, Germany, Ethiopia | G9: 44447 | H9: 1993 | I9: TV-MA | J9: 125 min | K9: Dramas, Independent Movies, International Movies | L9: On a photo shoot in Ghana, an American model slips back in time, becomes enslaved on a plantation and bears witness to the agony of her ancestral past.
A10: s9 | B10: TV Show | C10: The Great British Baking Show | D10: Andy Devonshire | E10: Mel Giedroyc, Sue Perkins, Mary Berry, Paul Hollywood | F10: United Kingdom | G10: 44448 | H10: 2021 | I10: TV-14 | J10: 9 Seasons | K10: British TV Shows, Reality TV | L10: A talented batch of amateur bakers face off in a 10-week competition, whipping up their best dishes in the hopes of being named the U.K.'s best.
A11: s10 | B11: Movie | C11: The Starling | D11: Theodore Melfi | E11: Melissa McCarthy, Chris O'Dowd, Kevin Kline, Timothy Olyphant, Daveed Diggs, Skyler Gisondo, Laura Harrier, Rosalind Chao, Kimberly Quinn, Loretta Devine, Ravi Kapoor | F11: United States | G11: 44449 | H11: 2021 | I11: PG-13 | J11: 104 min | K11: Comedies, Dramas | L11: A woman adjusting to life after a loss contends with a feisty bird that's taken over her garden â€” and a husband who's struggling to find a way forward.
A12: s11 | B12: TV Show | C12: Vendetta: Truth, Lies and The Mafia | D12: unknown | E12: unknown | F12: United States | G12: 44450 | H12: 2021 | I12: TV-MA | J12: 1 Season | K12: Crime TV Shows, Docuseries, International TV Shows | L12: Sicily boasts a bold "Anti-Mafia" coalition. But what happens when those trying to bring down organized crime are accused of being criminals themselves?
A13: s13 | B13: Movie | C13: Je Suis Karl | D13: Christian Schwochow | E13: Luna Wedler, Jannis NiewÃ¶hner, Milan Peschel, Edin HasanoviÄ‡, Anna FialovÃ¡, Marlon Boess, Victor Boccard, Fleur Geffrier, Aziz Dyab, MÃ©lanie FouchÃ©, Elizaveta MaximovÃ¡ | F13: United States | G13: 44451 | H13: 2021 | I13: TV-MA | J13: 127 min | K13: Dramas, International Movies | L13: After most of her family is murdered in a terrorist bombing, a young woman is unknowingly lured into joining the very group that killed them.
... A353: s2779 | B353: Movie | C353: Bethany Hamilton: Unstoppable | D353: Aaron Lieber | E353: Bethany Hamilton | F353: United States | G353: 44791 | H353: 2019 | I353: PG | J353: 100 min | K353: Children & Family Movies, Documentaries, Sports Movies | L353: This documentary follows the rising tide of Bethany Hamilton who lost her arm as a teen before making waves in pro surfing and her personal life.
A354: s2799 | B354: Movie | C354: 3022 | D354: John Suits | E354: Omar Epps, Kate Walsh, Miranda Cosgrove, Angus Macfadyen, Jorja Fox, Enver Gjokaj, Haaz Sleiman | F354: United States | G354: 44792 | H354: 2019 | I354: R | J354: 91 min | K354: Independent Movies, Sci-Fi & Fantasy, Thrillers | L354: Stranded when the Earth is suddenly destroyed in a mysterious cataclysm, the astronauts aboard a marooned space station slowly lose their minds.
A355: s2804 | B355: Movie | C355: Lu Over the Wall | D355: Masaaki Yuasa | E355: Kanon Tani, Shota Shimoda, Shinichi Shinohara, Akira Emoto, Soma Saito, Minako Kotobuki, Daigo, Nobu | F355: United States | G355: 44793 | H355: 2017 | I355: PG | J355: 113 min | K355: Anime Features, Music & Musicals, Sci-Fi & Fantasy | L355: Middle schooler Kai's depressing life in a boring fishing village changes drastically when a local mermaid named Lu joins his band.
A356: s2881 | B356: TV Show | C356: I Am Not Okay With This | D356: unknown | E356: Sophia Lillis, Wyatt Oleff, Kathleen Rose Perkins, Sofia Bryant, Richard Ellis, Sophia Tatum, David Theune, Zachary S. Williams, Aidan Wojtak-Hissong | F356: United States | G356: 44794 | H356: 2020 | I356: TV-MA | J356: 1 Season | K356: TV Comedies, TV Dramas, TV Sci-Fi & Fantasy | L356: Angsty Syd navigates high school awkwardness, family drama and an unrequited crush on her best friend while trying to rein in her budding superpowers.
A357: s2948 | B357: TV Show | C357: Arrow | D357: James Bamford | E357: Stephen Amell, Katie Cassidy, David Ramsey, Willa Holland, Paul Blackthorne, Emily Bett Rickards, John Barrowman, Colton Haynes, Susanna Thompson, Anna Hopkins, Juliana Harkavy, Adrian Holmes, Kathleen Gati, Echo Kellum, Rick Gonzalez, Dominic Bogart, Manu Bennett | F357: United States | G357: 44795 | H357: 2019 | I357: TV-14 | J357: 8 Seasons | K357: Crime TV Shows, TV Action & Adventure | L357: Based on DC Comics' Green Arrow, an affluent playboy becomes a vengeful superhero, saving the city from villains armed with just a bow and arrows.
A358: s2952 | B358: Movie | C358: Faith, Hope & Love | D358: Robert Krantz | E358: Robert Krantz, Peta Murgatroyd, Corbin Bernsen, Michael Richards, Nancy Stafford | F358: United States | G358: 44796 | H358: 2019 | I358: PG | J358: 106 min | K358: Comedies, Faith & Spirituality, Romantic Movies | L358: After shattering losses, a recent divorcÃ©e and a heartbroken widower restore their lives when they partner for a dance competition to save her studio.
A359: s2963 | B359: TV Show | C359: Miraculous: Tales of Ladybug & Cat Noir | D359: Thomas Astruc | E359: Cristina Vee, Bryce Papenbrook, Keith Silverstein, Mela Lee, Max Mittelman, Carrie Keranen, Stephanie Sheh, AndrÃ© Gordon, Matthew Mercer, Christopher Corey Smith, Philece Sampler, Selah Victor, Marieve Herington, Ben Diskin, Kira Buckland, Erin Fitzgerald, Grant George, Ethan Murray, David Roach, Todd Haberkorn | F359: United States | G359: 44797 | H359: 2019 | I359: TV-Y7 | J359: 5 Seasons | K359: Kids' TV, TV Action & Adventure | L359: When Paris is in peril, Marinette becomes Ladybug. Little does she know, her school crush Adrien is actually Cat Noir, another city-saving superhero.
A360: s3027 | B360: Movie | C360: The Brave | D360: William Kaufman | E360: Armand Assante, Louis Mandylor, Yuriy Kutsenko, Ravshana Kurkova, Igor Jijikine, Ivan Makarevich, Bessart Kallaku, Ervin Bejleri | F360: United States | G360: 44798 | H360: 2019 | I360: TV-MA | J360: 103 min | K360: Action & Adventure, Independent Movies | L360: With entry into the European Union at stake, Albania must rely on a mash-up of elite cops to take down a slippery drug lord dominating its economy.
A361: s3041 | B361: TV Show | C361: Until Dawn | D361: unknown | E361: Ahmed Sylla, Alban Ivanov, Ornella Fleury, Natoo, Carlito, Mcfly, Djimo, Lola Dubini, Noom Diawara, Tania Dutel, Hakim Jemili, Jason Brokerss, BÃ©rengÃ¨re Krief, Thomas Vandenberghe, Monsieur Poulpe, Jhon Rachid, Audrey Pirault, Jeanfi Janssens, Fadily Camara, Laurie Peret, Issa Doumbia, Anne-Sophie Girard, Elhadj Gaye, Guillaume Bats | F361: United States | G361: 44799 | H361: 2020 | I361: TV-MA | J361: 1 Season | K361: International TV Shows, Reality TV, TV Comedies | L361: Franceâ€™s funniest comics carry out ghastly tasks as they try to outlast â€“ and outwit â€“ one another while overnighting in haunted locations.
A362: s3043 | B362: TV Show | C362: Cheer | D362: unknown | E362: unknown | F362: United States | G362: 44800 | H362: 2020 | I362: TV-MA | J362: 1 Season | K362: Docuseries, Reality TV, Teen TV Shows | L362: This gripping docuseries follows the ups and downs of Navarro College's competitive cheer squad as they work to win a coveted national title.
A363: s3054 | B363: TV Show | C363: Border Security: America's Front Line | D363: unknown | E363: unknown | F363: United States | G363: 44801 | H363: 2018 | I363: TV-14 | J363: 1 Season | K363: Crime TV Shows, International TV Shows, Reality TV | L363: This reality series chronicles the behind-the-scenes action as U.S. Customs and Border Protection agents safeguard the nation's crossings and ports.
A364: s3056 | B364: TV Show | C364: Cells at Work! | D364: unknown | E364: Kana Hanazawa, Tomoaki Maeno, Daisuke Ono, Kikuko Inoue, Maria Naganawa, Takahiro Sakurai, Saori Hayami, Nobuhiko Okamoto, Yuichi Nakamura, Shoya Chiba, Mãƒ»Aãƒ»O, Ayako Kawasumi, Aya Endo, Hiroyuki Yoshino, Mamiko Noto | F364: United States | G364: 44802 | H364: 2018 | I364: TV-PG | J364: 1 Season | K364: Anime Series, Teen TV Shows | L364: One newcomer red blood cell just wants to do her job. Between bacteria incursions and meeting a certain white blood cell, she's got a lot to learn!
A365: s3097 | B365: TV Show | C365: You | D365: Lee Toland Krieger | E365: Penn Badgley, Elizabeth Lail, Shay Mitchell, John Stamos, Luca Padovan, Zach Cherry | F365: United States | G365: 44803 | H365: 2019 | I365: TV-MA | J365: 2 Seasons | K365: Crime TV Shows, Romantic TV Shows, TV Dramas | L365: Obsessed with an aspiring writer, a charming bookstore manager goes to extreme measures to insert himself into her life.
A366: s3099 | B366: Movie | C366: Fireworks | D366: Akiyuki Shinbo, Nobuyuki Takeuchi | E366: Yuki Kaji, Nobuo Tobita, Michiko Neya, Mitsuru Miyamoto, Fumihiko Tachiki, Shintaro Asanuma, Takahiro Sakurai, Kana Hanazawa, Toshiyuki Toyonaga, Suzu Hirose, Shinichiro Miki, Mamoru Miyano, Takako Matsu, Masaki Suda | F366: United States | G366: 44804 | H366: 2017 | I366: TV-PG | J366: 91 min | K366: Anime Features, Romantic Movies | L366: Middle schooler Nazuna desperately wants to run away with her classmate Norimichi, who somehow turns back time on this fateful summer's day.
... A515: s8803 | B515: Movie | C515: Zodiac | D515: David Fincher | E515: Mark Ruffalo, Jake Gyllenhaal, Robert Downey Jr., Anthony Edwards, Brian Cox, Elias Koteas, Donal Logue, John Carroll Lynch, Dermot Mulroney, ChloÃ« Sevigny | F515: United States | G515: 44953 | H515: 2007 | I515: R | J515: 158 min | K515: Cult Movies, Dramas, Thrillers | L515: A political cartoonist, a crime reporter and a pair of cops investigate San Francisco's infamous Zodiac Killer in this thriller based on a true story.

Sheet Cleaned-data
A1: title | B1: director | C1: country | D1: date | F1: tr | G1: trim_title | H1: trim_director | I1: trim_country | J1: trim_date
A2: Dick Johnson Is Dead | C2: Kirsten Johnson | D2: United States | E2: 44440 | G2: =TRIM(A2) -> Dick Johnson Is Dead | H2: =IF('Cleaned-data'!C2="unknown","Unknown",PROPER(TRIM('Cleaned-data'!C2))) -> Kirsten Johnson | I2: =TRIM(D2) -> United States | J2: 44440
A3: Blood & Water | C3: unknown | D3: United States | E3: 44441 | G3: =TRIM(A3) -> Blood & Water | H3: =IF('Cleaned-data'!C3="unknown","Unknown",PROPER(TRIM('Cleaned-data'!C3))) -> Unknown | I3: =TRIM(D3) -> United States | J3: 44441
A4: Ganglands | C4: Julien Leclercq | D4: United States | E4: 44442 | G4: =TRIM(A4) -> Ganglands | H4: =IF('Cleaned-data'!C4="unknown","Unknown",PROPER(TRIM('Cleaned-data'!C4))) -> Julien Leclercq | I4: =TRIM(D4) -> United States | J4: 44442
A5: Jailbirds New Orleans | C5: unknown | D5: United States | E5: 44443 | G5: =TRIM(A5) -> Jailbirds New Orleans | H5: =IF('Cleaned-data'!C5="unknown","Unknown",PROPER(TRIM('Cleaned-data'!C5))) -> Unknown | I5: =TRIM(D5) -> United States | J5: 44443
A6: Kota Factory | C6: unknown | D6: United States | E6: 44444 | G6: =TRIM(A6) -> Kota Factory | H6: =IF('Cleaned-data'!C6="unknown","Unknown",PROPER(TRIM('Cleaned-data'!C6))) -> Unknown | I6: =TRIM(D6) -> United States | J6: 44444
A7: Midnight Mass | C7: Mike Flanagan | D7: United States | E7: 44445 | G7: =TRIM(A7) -> Midnight Mass | H7: =IF('Cleaned-data'!C7="unknown","Unknown",PROPER(TRIM('Cleaned-data'!C7))) -> Mike Flanagan | I7: =TRIM(D7) -> United States | J7: 44445
A8: My Little Pony: A New Generation | C8: Robert Cullen, JosÃ© Luis Ucha | D8: United States | E8: 44446 | G8: =TRIM(A8) -> My Little Pony: A New Generation | H8: =IF('Cleaned-data'!C8="unknown","Unknown",PROPER(TRIM('Cleaned-data'!C8))) -> Robert Cullen, Josã© Luis Ucha | I8: =TRIM(D8) -> United States | J8: 44446
A9: Sankofa | C9: Haile Gerima | D9: United States | E9: 44447 | G9: =TRIM(A9) -> Sankofa | H9: =IF('Cleaned-data'!C9="unknown","Unknown",PROPER(TRIM('Cleaned-data'!C9))) -> Haile Gerima | I9: =TRIM(D9) -> United States | J9: 44447
A10: The Great British Baking Show | C10: Andy Devonshire | D10: United States | E10: 44448 | G10: =TRIM(A10) -> The Great British Baking Show | H10: =IF('Cleaned-data'!C10="unknown","Unknown",PROPER(TRIM('Cleaned-data'!C10))) -> Andy Devonshire | I10: =TRIM(D10) -> United States | J10: 44448
A11: The Starling | C11: Theodore Melfi | D11: United States | E11: 44449 | G11: =TRIM(A11) -> The Starling | H11: =IF('Cleaned-data'!C11="unknown","Unknown",PROPER(TRIM('Cleaned-data'!C11))) -> Theodore Melfi | I11: =TRIM(D11) -> United States | J11: 44449
A12: Vendetta: Truth, Lies and The Mafia | C12: unknown | D12: United States | E12: 44450 | G12: =TRIM(A12) -> Vendetta: Truth, Lies and The Mafia | H12: =IF('Cleaned-data'!C12="unknown","Unknown",PROPER(TRIM('Cleaned-data'!C12))) -> Unknown | I12: =TRIM(D12) -> United States | J12: 44450
A13: Je Suis Karl | C13: Christian Schwochow | D13: United States | E13: 44451 | G13: =TRIM(A13) -> Je Suis Karl | H13: =IF('Cleaned-data'!C13="unknown","Unknown",PROPER(TRIM('Cleaned-data'!C13))) -> Christian Schwochow | I13: =TRIM(D13) -> United States | J13: 44451
... A353: Bethany Hamilton: Unstoppable | C353: Aaron Lieber | D353: United States | E353: 44791 | G353: =TRIM(A353) -> Bethany Hamilton: Unstoppable | H353: =IF('Cleaned-data'!C353="unknown","Unknown",PROPER(TRIM('Cleaned-data'!C353))) -> Aaron Lieber | I353: =TRIM(D353) -> United States | J353: 44791
A354: 3022 | C354: John Suits | D354: United States | E354: 44792 | G354: =TRIM(A354) -> 3022 | H354: =IF('Cleaned-data'!C354="unknown","Unknown",PROPER(TRIM('Cleaned-data'!C354))) -> John Suits | I354: =TRIM(D354) -> United States | J354: 44792
A355: Lu Over the Wall | C355: Masaaki Yuasa | D355: United States | E355: 44793 | G355: =TRIM(A355) -> Lu Over the Wall | H355: =IF('Cleaned-data'!C355="unknown","Unknown",PROPER(TRIM('Cleaned-data'!C355))) -> Masaaki Yuasa | I355: =TRIM(D355) -> United States | J355: 44793
A356: I Am Not Okay With This | C356: unknown | D356: United States | E356: 44794 | G356: =TRIM(A356) -> I Am Not Okay With This | H356: =IF('Cleaned-data'!C356="unknown","Unknown",PROPER(TRIM('Cleaned-data'!C356))) -> Unknown | I356: =TRIM(D356) -> United States | J356: 44794
A357: Arrow | C357: James Bamford | D357: United States | E357: 44795 | G357: =TRIM(A357) -> Arrow | H357: =IF('Cleaned-data'!C357="unknown","Unknown",PROPER(TRIM('Cleaned-data'!C357))) -> James Bamford | I357: =TRIM(D357) -> United States | J357: 44795
A358: Faith, Hope & Love | C358: Robert Krantz | D358: United States | E358: 44796 | G358: =TRIM(A358) -> Faith, Hope & Love | H358: =IF('Cleaned-data'!C358="unknown","Unknown",PROPER(TRIM('Cleaned-data'!C358))) -> Robert Krantz | I358: =TRIM(D358) -> United States | J358: 44796
A359: Miraculous: Tales of Ladybug & Cat Noir | C359: Thomas Astruc | D359: United States | E359: 44797 | G359: =TRIM(A359) -> Miraculous: Tales of Ladybug & Cat Noir | H359: =IF('Cleaned-data'!C359="unknown","Unknown",PROPER(TRIM('Cleaned-data'!C359))) -> Thomas Astruc | I359: =TRIM(D359) -> United States | J359: 44797
A360: The Brave | C360: William Kaufman | D360: United States | E360: 44798 | G360: =TRIM(A360) -> The Brave | H360: =IF('Cleaned-data'!C360="unknown","Unknown",PROPER(TRIM('Cleaned-data'!C360))) -> William Kaufman | I360: =TRIM(D360) -> United States | J360: 44798
A361: Until Dawn | C361: unknown | D361: United States | E361: 44799 | G361: =TRIM(A361) -> Until Dawn | H361: =IF('Cleaned-data'!C361="unknown","Unknown",PROPER(TRIM('Cleaned-data'!C361))) -> Unknown | I361: =TRIM(D361) -> United States | J361: 44799
A362: Cheer | C362: unknown | D362: United States | E362: 44800 | G362: =TRIM(A362) -> Cheer | H362: =IF('Cleaned-data'!C362="unknown","Unknown",PROPER(TRIM('Cleaned-data'!C362))) -> Unknown | I362: =TRIM(D362) -> United States | J362: 44800
A363: Border Security: America's Front Line | C363: unknown | D363: United States | E363: 44801 | G363: =TRIM(A363) -> Border Security: America's Front Line | H363: =IF('Cleaned-data'!C363="unknown","Unknown",PROPER(TRIM('Cleaned-data'!C363))) -> Unknown | I363: =TRIM(D363) -> United States | J363: 44801
A364: Cells at Work! | C364: unknown | D364: United States | E364: 44802 | G364: =TRIM(A364) -> Cells at Work! | H364: =IF('Cleaned-data'!C364="unknown","Unknown",PROPER(TRIM('Cleaned-data'!C364))) -> Unknown | I364: =TRIM(D364) -> United States | J364: 44802
A365: You | C365: Lee Toland Krieger | D365: United States | E365: 44803 | G365: =TRIM(A365) -> You | H365: =IF('Cleaned-data'!C365="unknown","Unknown",PROPER(TRIM('Cleaned-data'!C365))) -> Lee Toland Krieger | I365: =TRIM(D365) -> United States | J365: 44803
A366: Fireworks | C366: Akiyuki Shinbo, Nobuyuki Takeuchi | D366: United States | E366: 44804 | G366: =TRIM(A366) -> Fireworks | H366: =IF('Cleaned-data'!C366="unknown","Unknown",PROPER(TRIM('Cleaned-data'!C366))) -> Akiyuki Shinbo, Nobuyuki Takeuchi | I366: =TRIM(D366) -> United States | J366: 44804
... A515: Zodiac | C515: David Fincher | D515: United States | E515: 44953 | G515: =TRIM(A515) -> Zodiac | H515: =IF('Cleaned-data'!C515="unknown","Unknown",PROPER(TRIM('Cleaned-data'!C515))) -> David Fincher | I515: =TRIM(D515) -> United States | J515: 44953
